mktrader/__init__.py
mktrader/brokers.py
mktrader/engines.py
mktrader/feeds.py
mktrader/helpers.py
mktrader/indicators.py
mktrader/logger.py
mktrader/models.py
mktrader/strategies.py
mktrader-0.0.1.dist-info/LICENSE
mktrader-0.0.1.dist-info/METADATA
mktrader-0.0.1.dist-info/WHEEL
mktrader-0.0.1.dist-info/top_level.txt
mktrader-0.0.1.dist-info/RECORD
