Metadata-Version: 2.1
Name: mktrader
Version: 0.0.1
Summary: Stock Market Trading Framework
Author: Matthew K Murphy (MatthewKurtis)
Author-email: <mkmurphy526@gmail.com>
Keywords: python,trading,stock,market
Classifier: Development Status :: 1 - Planning
Classifier: Intended Audience :: Financial and Insurance Industry
Classifier: Programming Language :: Python :: 3
Classifier: Operating System :: Unix
Classifier: Operating System :: MacOS :: MacOS X
Classifier: Operating System :: Microsoft :: Windows
License-File: LICENSE
Requires-Dist: websocket-client
